controller.v
module controller (
    input clk,
    input rst,
    input [2:0] opcode,
    input is_zero,
    output reg sel,
    output reg rd,
    output reg ld_ir,
    output reg halt,
    output reg inc_pc,
    output reg ld_ac,
    output reg ld_pc,
    output reg wr,
    output reg data_e
);

    parameter INST_ADDR  = 3'b000;
    parameter INST_FETCH = 3'b001;
    parameter INST_LOAD  = 3'b010;
    parameter IDLE       = 3'b011;
    parameter OP_ADDR    = 3'b100;
    parameter OP_FETCH   = 3'b101;
    parameter ALU_OP     = 3'b110;
    parameter STORE      = 3'b111;

    parameter HLT = 3'b000;
    parameter SKZ = 3'b001;
    parameter ADD = 3'b010;
    parameter AND = 3'b011;
    parameter XOR = 3'b100;
    parameter LDA = 3'b101;
    parameter STO = 3'b110;
    parameter JMP = 3'b111;

    reg [2:0] state;

    always @(posedge clk) begin
        if (rst) begin
            state <= INST_ADDR;
        end else begin
            state <= state + 1'b1;
        end
    end

    always @(state, opcode, is_zero) begin

        case (state)
            INST_ADDR: begin
                sel    = 1'b1;
                rd     = 1'b0;
                ld_ir  = 1'b0;
                halt   = 1'b0;
                inc_pc = 1'b0;
                ld_ac  = 1'b0;
                ld_pc  = 1'b0;
                wr     = 1'b0;
                data_e = 1'b0;
                
            end
            INST_FETCH: begin
                sel    = 1'b1;
                rd     = 1'b1;
                ld_ir  = 1'b0;
                halt   = 1'b0;
                inc_pc = 1'b0;
                ld_ac  = 1'b0;
                ld_pc  = 1'b0;
                wr     = 1'b0;
                data_e = 1'b0;
            end
            INST_LOAD: begin
                sel    = 1'b1;
                rd     = 1'b1;
                ld_ir  = 1'b1;
                halt   = 1'b0;
                inc_pc = 1'b0;
                ld_ac  = 1'b0;
                ld_pc  = 1'b0;
                wr     = 1'b0;
                data_e = 1'b0;
            end
            IDLE: begin
                sel    = 1'b1;
                rd     = 1'b1;
                ld_ir  = 1'b1;
                halt   = 1'b0;
                inc_pc = 1'b0;
                ld_ac  = 1'b0;
                ld_pc  = 1'b0;
                wr     = 1'b0;
                data_e = 1'b0;
            end
            OP_ADDR: begin
                sel    = 1'b0;
                rd     = 1'b0;
                ld_ir  = 1'b0;
                
                if (opcode == HLT) begin
                    halt = 1'b1;
                end else begin
                    halt = 1'b0;
                end
                
                inc_pc = 1'b1;
                ld_ac  = 1'b0;
                ld_pc  = 1'b0;
                wr     = 1'b0;
                data_e = 1'b0;
            end
            OP_FETCH: begin
                sel = 1'b0;
                if (opcode == ADD || opcode == AND || opcode == XOR || opcode == LDA) begin
                    rd = 1'b1;
                end else begin
                    rd = 1'b0;
                end

                ld_ir  = 1'b0;
                halt   = 1'b0;
                inc_pc = 1'b0;
                ld_ac  = 1'b0;
                ld_pc  = 1'b0;
                wr     = 1'b0;
                data_e = 1'b0;
            end
            ALU_OP: begin
                sel = 1'b0;
                if (opcode == ADD || opcode == AND || opcode == XOR || opcode == LDA) begin
                    rd = 1'b1;
                end else begin
                    rd = 1'b0;
                end

                ld_ir  = 1'b0;
                halt   = 1'b0;

                if (opcode == (SKZ && is_zero)) begin
                    inc_pc = 1'b1;
                end else begin
                    inc_pc = 1'b0;
                end
                ld_ac  = 1'b0;


                if (opcode == JMP) begin
                    ld_pc = 1'b1;
                end else begin
                    ld_pc = 1'b0;
                end

                wr     = 1'b0;

                if (opcode == STO) begin
                    data_e = 1'b1;
                end else begin
                    data_e = 1'b0;
                end
            end
            STORE: begin
                sel = 1'b0;
                if (opcode == ADD || opcode == AND || opcode == XOR || opcode == LDA) begin
                    rd    = 1'b1;
                    ld_ac = 1'b1;
                end else begin
                    rd    = 1'b0;
                    ld_ac = 1'b0;
                end

                ld_ir  = 1'b0;
                halt   = 1'b0;
                inc_pc = 1'b0;


                if (opcode == JMP) begin
                    ld_pc = 1'b1;
                end else begin
                    ld_pc = 1'b0;
                end

                if (opcode == STO) begin
                    wr     = 1'b1;
                    data_e = 1'b1;
                end else begin
                    wr     = 1'b0;
                    data_e = 1'b0;
                end
            end
            default: begin
                sel    = 1'b0;
                rd     = 1'b0;
                ld_ir  = 1'b0;
                halt   = 1'b0;
                inc_pc = 1'b0;
                ld_ac  = 1'b0;
                ld_pc  = 1'b0;
                wr     = 1'b0;
                data_e = 1'b0;
            end
        endcase
    end

endmodule

alu.v
module alu (
    input [2:0] opcode,
    input [7:0] inA,
    input [7:0] inB,
    output reg [7:0] out,
    output is_zero
);

    parameter HLT = 3'b000;
    parameter SKZ = 3'b001;
    parameter ADD = 3'b010;
    parameter AND = 3'b011;
    parameter XOR = 3'b100;
    parameter LDA = 3'b101;
    parameter STO = 3'b110;
    parameter JMP = 3'b111;

    assign is_zero = (inA == 8'b00000000) ? 1'b1 : 1'b0;

    always @(opcode, inA, inB) begin
        case (opcode)
            HLT: out = inA;
            SKZ: out = inA;
            ADD: out = inA + inB;
            AND: out = inA & inB;
            XOR: out = inA ^ inB;
            LDA: out = inB;
            STO: out = inA;
            JMP: out = inA;
            default: out = inA;
        endcase
    end

endmodule

register.v
module register #(parameter WIDTH = 8) (
    input clk,
    input rst,
    input ld,
    input [WIDTH-1:0] data_in,
    output reg [WIDTH-1:0] data_out
);

    always @(posedge clk) begin
        if (rst) begin
            data_out <= {WIDTH{1'b0}};
        end else if (ld) begin
            data_out <= data_in;
        end else begin
            data_out <= data_out;
        end
    end

endmodule

memory.v
// module memory (
//     input clk,
//     input rd,
//     input wr,
//     input [4:0] addr,
//     inout [7:0] data
// );

//     reg [7:0] ram [0:31];
//     reg [7:0] data_out;

//     assign data = (rd && !wr) ? data_out : 8'bzzzzzzzz;

//     always @(posedge clk) begin
//         if (wr && !rd) begin
//             ram[addr] <= data;
//         end else begin
//             ram[addr] <= ram[addr];
//         end
//     end

//     always @(posedge clk) begin
//         if (rd && !wr) begin
//             data_out <= ram[addr];
//         end else begin
//             data_out <= data_out;
//         end
//     end

// endmodule

module memory #(
    parameter INIT_FILE = "PROG1.txt"
) (
    input clk,
    input rd,
    input wr,
    input [4:0] addr,
    inout [7:0] data
);

    reg [7:0] ram [0:31];
    reg [7:0] data_out;
    integer index;

    assign data = (rd && !wr) ? data_out : 8'bzzzzzzzz;

    initial begin
        // for (index = 0; index < 32; index = index + 1) begin
        //     ram[index] = 8'h00;
        // end
        $readmemb(INIT_FILE, ram);
    end

    always @(posedge clk) begin
        if (wr && !rd) begin
            ram[addr] <= data;
        end else begin
            ram[addr] <= ram[addr];
        end
    end

    always @(posedge clk) begin
        if (rd && !wr) begin
            data_out <= ram[addr];
        end else begin
            data_out <= data_out;
        end
    end

endmodule

address_mux.v
module address_mux #(parameter WIDTH = 5) (
    input [WIDTH-1:0] inst_addr,
    input [WIDTH-1:0] op_addr,
    input sel,
    output [WIDTH-1:0] addr
);

    // sel = 1 for instruction address, sel = 0 for operand address
    assign addr = sel ? inst_addr : op_addr;

endmodule

program_counter.v
module program_counter (
    input clk,
    input rst,
    input ld_pc,
    input inc_pc,
    input [4:0] in_pc,
    output reg [4:0] pc
);

    always @(posedge clk) begin
        if (rst) begin
            pc <= 5'b00000;
        end else if (ld_pc) begin
            pc <= in_pc;
        end else if (inc_pc) begin
            pc <= pc + 1'b1;
        end else begin
            pc <= pc;
        end
    end

endmodule

risc_cpu.v
module risc_cpu (
    input clk,
    input rst,
    output halt
);

    wire [4:0] pc_out;
    wire [4:0] addr_mux_out;
    wire [7:0] ir_out;
    wire [7:0] ac_out;
    wire [7:0] alu_out;
    wire [7:0] mem_data;
    
    wire sel;
    wire rd;
    wire wr;
    wire ld_ir;
    wire ld_ac;
    wire ld_pc;
    wire inc_pc;
    wire data_e;
    wire is_zero;

    assign mem_data = data_e ? ac_out : 8'bzzzzzzzz;

    program_counter pc_inst (
        .clk(clk),
        .rst(rst),
        .ld_pc(ld_pc),
        .inc_pc(inc_pc),
        .in_pc(ir_out[4:0]),
        .pc(pc_out)
    );

    address_mux #(.WIDTH(5)) addr_mux_inst (
        .inst_addr(pc_out),
        .op_addr(ir_out[4:0]),
        .sel(sel),
        .addr(addr_mux_out)
    );

    memory mem_inst (
        .clk(clk),
        .rd(rd),
        .wr(wr),
        .addr(addr_mux_out),
        .data(mem_data)
    );

    register #(.WIDTH(8)) ir_inst (
        .clk(clk),
        .rst(rst),
        .ld(ld_ir),
        .data_in(mem_data),
        .data_out(ir_out)
    );

    register #(.WIDTH(8)) ac_inst (
        .clk(clk),
        .rst(rst),
        .ld(ld_ac),
        .data_in(alu_out),
        .data_out(ac_out)
    );

    alu alu_inst (
        .opcode(ir_out[7:5]),
        .inA(ac_out),
        .inB(mem_data),
        .out(alu_out),
        .is_zero(is_zero)
    );

    controller ctrl_inst (
        .clk(clk),
        .rst(rst),
        .opcode(ir_out[7:5]),
        .is_zero(is_zero),
        .sel(sel),
        .rd(rd),
        .ld_ir(ld_ir),
        .halt(halt),
        .inc_pc(inc_pc),
        .ld_ac(ld_ac),
        .ld_pc(ld_pc),
        .wr(wr),
        .data_e(data_e)
    );

endmodule

tb_risc_cpu.v
`timescale 1ns/1ps

module tb_risc_cpu;

    reg clk;
    reg rst;
    wire halt;
    integer cycles;
    integer i;
    integer done;
    integer total_fail;
    integer test_fail;

    // opcode_seen[opcode] = 1 when that opcode executed at least once
    reg [7:0] opcode_seen;

    // Opcode map (same as controller/alu)
    localparam HLT = 3'b000;
    localparam SKZ = 3'b001;
    localparam ADD = 3'b010;
    localparam AND = 3'b011;
    localparam XOR = 3'b100;
    localparam LDA = 3'b101;
    localparam STO = 3'b110;
    localparam JMP = 3'b111;

    // Limit each run so bad programs do not hang forever
    localparam MAX_CYCLES = 2000;

    risc_cpu dut (
        .clk(clk),
        .rst(rst),
        .halt(halt)
    );

    initial begin
        clk = 1'b0;
        forever #5 clk = ~clk;
    end

    task expect_mem;
        input [4:0] addr;
        input [7:0] expected;
        input [8*32-1:0] tag;
        begin
            if (dut.mem_inst.ram[addr] !== expected) begin
                $display("[FAIL] %0s M[%0d]=0x%02x expected=0x%02x",
                         tag, addr, dut.mem_inst.ram[addr], expected);
                total_fail = total_fail + 1;
                test_fail = test_fail + 1;
            end else begin
                $display("[PASS] %0s M[%0d]=0x%02x", tag, addr, dut.mem_inst.ram[addr]);
            end
        end
    endtask

    task run_one_program;
        input [8*64-1:0] prog_file;
        input [4:0] expected_halt_pc;
        input [7:0] required_ops_mask;
        input [7:0] exact_ops_mask;
        begin
            test_fail = 0;
            $display("");
            $display("========== Running %0s ==========", prog_file);

            // Clear RAM so each test starts clean
            for (i = 0; i < 32; i = i + 1) begin
                dut.mem_inst.ram[i] = 8'h00;
            end

            // Load this program image
            $readmemb(prog_file, dut.mem_inst.ram);

            // Reset coverage and CPU
            opcode_seen = 8'h00;
            rst = 1'b1;
            repeat (2) @(posedge clk);
            rst = 1'b0;

            // Run until HLT decode at OP_ADDR or timeout
            cycles = 0;
            done = 0;
            while (!done && (cycles < MAX_CYCLES)) begin
                @(posedge clk);
                #1;
                cycles = cycles + 1;

                if (!rst && (dut.ctrl_inst.state == dut.ctrl_inst.OP_ADDR)) begin
                    opcode_seen[dut.ir_out[7:5]] = 1'b1;
                    if (dut.ir_out[7:5] == HLT) begin
                        done = 1;
                    end
                end
            end

            if (!done) begin
                $display("[FAIL] %0s timed out after %0d cycles", prog_file, MAX_CYCLES);
                total_fail = total_fail + 1;
                test_fail = test_fail + 1;
            end else begin
                $display("[PASS] %0s reached HLT in %0d cycles", prog_file, cycles);
            end

            if (dut.pc_out !== expected_halt_pc) begin
                $display("[FAIL] %0s halt PC=%0d expected=%0d", prog_file, dut.pc_out, expected_halt_pc);
                total_fail = total_fail + 1;
                test_fail = test_fail + 1;
            end else begin
                $display("[PASS] %0s halt PC=%0d", prog_file, dut.pc_out);
            end

            // Operation coverage checks for this program
            if ((opcode_seen & required_ops_mask) != required_ops_mask) begin
                $display("[FAIL] %0s missing required operations. seen=%b required=%b",
                         prog_file, opcode_seen, required_ops_mask);
                total_fail = total_fail + 1;
                test_fail = test_fail + 1;
            end else begin
                $display("[PASS] %0s required operation coverage ok. seen=%b", prog_file, opcode_seen);
            end

            if (opcode_seen !== exact_ops_mask) begin
                $display("[FAIL] %0s exact operation mask mismatch. seen=%b expected=%b",
                         prog_file, opcode_seen, exact_ops_mask);
                total_fail = total_fail + 1;
                test_fail = test_fail + 1;
            end else begin
                $display("[PASS] %0s exact operation mask ok. seen=%b", prog_file, opcode_seen);
            end

            if (test_fail == 0) begin
                $display("[PASS] %0s summary: all checks passed", prog_file);
            end else begin
                $display("[FAIL] %0s summary: %0d check(s) failed", prog_file, test_fail);
            end
        end
    endtask

    initial begin
        total_fail = 0;
        rst = 1'b0;

        // Bit index = opcode number:
        // bit0 HLT, bit1 SKZ, bit2 ADD, bit3 AND, bit4 XOR, bit5 LDA, bit6 STO, bit7 JMP

        // PROG1 expected pass point: HLT at address 0x17
        run_one_program("PROG1.txt", 5'h17, 8'b11110011, 8'b11110011);
        expect_mem(5'h1A, 8'h00, "PROG1 DATA_1");
        expect_mem(5'h1B, 8'hFF, "PROG1 DATA_2");
        expect_mem(5'h1C, 8'h00, "PROG1 TEMP");

        // PROG2 expected pass point: HLT at address 0x10
        run_one_program("PROG2.txt", 5'h10, 8'b11111111, 8'b11111111);
        expect_mem(5'h1A, 8'h01, "PROG2 DATA_1");
        expect_mem(5'h1B, 8'hAA, "PROG2 DATA_2");
        expect_mem(5'h1C, 8'hFF, "PROG2 DATA_3");
        expect_mem(5'h1D, 8'hFF, "PROG2 TEMP");

        // PROG3 expected pass point: HLT at address 0x0C
        run_one_program("PROG3.txt", 5'h0C, 8'b11110111, 8'b11110111);
        expect_mem(5'h1A, 8'h90, "PROG3 FN1");
        expect_mem(5'h1B, 8'hE9, "PROG3 FN2");
        expect_mem(5'h1C, 8'h90, "PROG3 TEMP");
        expect_mem(5'h1D, 8'h90, "PROG3 LIMIT");
        expect_mem(5'h1E, 8'h00, "PROG3 ZERO");
        expect_mem(5'h1F, 8'h01, "PROG3 ONE");

        if (total_fail == 0) begin
            $display("ALL PROGRAMS PASSED");
        end else begin
            $display("REGRESSION FAILED: %0d issue(s)", total_fail);
        end

        #20;
        $finish;
    end

    initial begin
        $dumpfile("risc_cpu.vcd");
        $dumpvars(0, tb_risc_cpu);
    end

endmodule

risc_cpu.vcd
$date
	Wed Apr 29 20:28:36 2026
$end
$version
	Icarus Verilog
$end
$timescale
	1ps
$end
$scope module tb_risc_cpu $end
$var wire 1 ! halt $end
$var reg 1 " clk $end
$var reg 8 # opcode_seen [7:0] $end
$var reg 1 $ rst $end
$var integer 32 % cycles [31:0] $end
$var integer 32 & done [31:0] $end
$var integer 32 ' i [31:0] $end
$var integer 32 ( test_fail [31:0] $end
$var integer 32 ) total_fail [31:0] $end
$scope module dut $end
$var wire 1 " clk $end
$var wire 8 * mem_data [7:0] $end
$var wire 1 $ rst $end
$var wire 1 + wr $end
$var wire 1 , sel $end
$var wire 1 - rd $end
$var wire 5 . pc_out [4:0] $end
$var wire 1 / ld_pc $end
$var wire 1 0 ld_ir $end
$var wire 1 1 ld_ac $end
$var wire 1 2 is_zero $end
$var wire 8 3 ir_out [7:0] $end
$var wire 1 4 inc_pc $end
$var wire 1 ! halt $end
$var wire 1 5 data_e $end
$var wire 8 6 alu_out [7:0] $end
$var wire 5 7 addr_mux_out [4:0] $end
$var wire 8 8 ac_out [7:0] $end
$scope module ac_inst $end
$var wire 1 " clk $end
$var wire 1 $ rst $end
$var wire 1 1 ld $end
$var wire 8 9 data_in [7:0] $end
$var reg 8 : data_out [7:0] $end
$upscope $end
$scope module addr_mux_inst $end
$var wire 5 ; op_addr [4:0] $end
$var wire 1 , sel $end
$var wire 5 < inst_addr [4:0] $end
$var wire 5 = addr [4:0] $end
$upscope $end
$scope module alu_inst $end
$var wire 8 > inA [7:0] $end
$var wire 8 ? inB [7:0] $end
$var wire 3 @ opcode [2:0] $end
$var wire 1 2 is_zero $end
$var reg 8 A out [7:0] $end
$upscope $end
$scope module ctrl_inst $end
$var wire 1 " clk $end
$var wire 1 2 is_zero $end
$var wire 3 B opcode [2:0] $end
$var wire 1 $ rst $end
$var reg 1 5 data_e $end
$var reg 1 ! halt $end
$var reg 1 4 inc_pc $end
$var reg 1 1 ld_ac $end
$var reg 1 0 ld_ir $end
$var reg 1 / ld_pc $end
$var reg 1 - rd $end
$var reg 1 , sel $end
$var reg 3 C state [2:0] $end
$var reg 1 + wr $end
$upscope $end
$scope module ir_inst $end
$var wire 1 " clk $end
$var wire 8 D data_in [7:0] $end
$var wire 1 0 ld $end
$var wire 1 $ rst $end
$var reg 8 E data_out [7:0] $end
$upscope $end
$scope module mem_inst $end
$var wire 5 F addr [4:0] $end
$var wire 1 " clk $end
$var wire 8 G data [7:0] $end
$var wire 1 - rd $end
$var wire 1 + wr $end
$var reg 8 H data_out [7:0] $end
$upscope $end
$scope module pc_inst $end
$var wire 1 " clk $end
$var wire 5 I in_pc [4:0] $end
$var wire 1 4 inc_pc $end
$var wire 1 / ld_pc $end
$var wire 1 $ rst $end
$var reg 5 J pc [4:0] $end
$upscope $end
$upscope $end
$scope task expect_mem $end
$var reg 5 K addr [4:0] $end
$var reg 8 L expected [7:0] $end
$var reg 256 M tag [255:0] $end
$upscope $end
$scope task run_one_program $end
$var reg 8 N exact_ops_mask [7:0] $end
$var reg 5 O expected_halt_pc [4:0] $end
$var reg 512 P prog_file [511:0] $end
$var reg 8 Q required_ops_mask [7:0] $end
$upscope $end
$upscope $end
$enddefinitions $end
#0
$dumpvars
b11110011 Q
b10100000101001001001111010001110011000100101110011101000111100001110100 P
b10111 O
b11110011 N
bx M
bx L
bx K
bx J
bx I
bx H
bz G
bx F
bx E
bz D
bx C
bx B
bx A
bx @
bz ?
bx >
bx =
bx <
bx ;
bx :
bx 9
bx 8
bx 7
bx 6
05
04
bx 3
x2
01
00
0/
bx .
0-
0,
0+
bz *
b0 )
b0 (
b100000 '
bx &
bx %
1$
b0 #
0"
0!
$end
#5000
b0 7
b0 =
b0 F
b0 B
b0 @
b0 ;
b0 I
b0 6
b0 9
b0 A
12
1,
b0 .
b0 <
b0 J
b0 3
b0 E
b0 8
b0 :
b0 >
b0 C
1"
#10000
0"
#15000
b0 &
b0 %
0$
1"
#20000
0"
#25000
bx *
bx ?
bx D
bx G
1-
b1 C
1"
#26000
b1 %
#30000
0"
#35000
10
b11111110 *
b11111110 ?
b11111110 D
b11111110 G
b10 C
b11111110 H
1"
#36000
b10 %
#40000
0"
#45000
b111 B
b111 @
b11110 ;
b11110 I
b11111110 3
b11111110 E
b11 C
1"
#46000
b11 %
#50000
0"
#55000
bz *
bz ?
bz D
bz G
b11110 7
b11110 =
b11110 F
14
00
0-
0,
b100 C
1"
#56000
b10000000 #
b100 %
#60000
0"
#65000
04
b1 .
b1 <
b1 J
b101 C
1"
#66000
b101 %
#70000
0"
#75000
1/
b110 C
1"
#76000
b110 %
#80000
0"
#85000
b11110 .
b11110 <
b11110 J
b111 C
1"
#86000
b111 %
#90000
0"
#95000
0/
1,
b0 C
1"
#96000
b1000 %
#100000
0"
#105000
b11111110 *
b11111110 ?
b11111110 D
b11111110 G
1-
b1 C
1"
#106000
b1001 %
#110000
0"
#115000
10
b11100011 *
b11100011 ?
b11100011 D
b11100011 G
b10 C
b11100011 H
1"
#116000
b1010 %
#120000
0"
#125000
b11 ;
b11 I
b11100011 3
b11100011 E
b11 C
1"
#126000
b1011 %
#130000
0"
#135000
bz *
bz ?
bz D
bz G
b11 7
b11 =
b11 F
14
00
0-
0,
b100 C
1"
#136000
b1100 %
#140000
0"
#145000
04
b11111 .
b11111 <
b11111 J
b101 C
1"
#146000
b1101 %
#150000
0"
#155000
1/
b110 C
1"
#156000
b1110 %
#160000
0"
#165000
b11 .
b11 <
b11 J
b111 C
1"
#166000
b1111 %
#170000
0"
#175000
0/
1,
b0 C
1"
#176000
b10000 %
#180000
0"
#185000
b11100011 *
b11100011 ?
b11100011 D
b11100011 G
1-
b1 C
1"
#186000
b10001 %
#190000
0"
#195000
10
b10111010 *
b10111010 ?
b10111010 D
b10111010 G
b10 C
b10111010 H
1"
#196000
b10010 %
#200000
0"
#205000
b10111010 6
b10111010 9
b10111010 A
b101 B
b101 @
b11010 ;
b11010 I
b10111010 3
b10111010 E
b11 C
1"
#206000
b10011 %
#210000
0"
#215000
bz 6
bz 9
bz A
bz *
bz ?
bz D
bz G
b11010 7
b11010 =
b11010 F
14
00
0-
0,
b100 C
1"
#216000
b10100000 #
b10100 %
#220000
0"
#225000
b10111010 6
b10111010 9
b10111010 A
b10111010 *
b10111010 ?
b10111010 D
b10111010 G
04
1-
b100 .
b100 <
b100 J
b101 C
1"
#226000
b10101 %
#230000
0"
#235000
b0 6
b0 9
b0 A
b0 *
b0 ?
b0 D
b0 G
b110 C
b0 H
1"
#236000
b10110 %
#240000
0"
#245000
11
b111 C
1"
#246000
b10111 %
#250000
0"
#255000
bz 6
bz 9
bz A
bz *
bz ?
bz D
bz G
b100 7
b100 =
b100 F
01
0-
1,
b0 C
1"
#256000
b11000 %
#260000
0"
#265000
b0 6
b0 9
b0 A
b0 *
b0 ?
b0 D
b0 G
1-
b1 C
1"
#266000
b11001 %
#270000
0"
#275000
b100000 6
b100000 9
b100000 A
10
b100000 *
b100000 ?
b100000 D
b100000 G
b10 C
b100000 H
1"
#276000
b11010 %
#280000
0"
#285000
b0 6
b0 9
b0 A
b1 B
b1 @
b0 ;
b0 I
b100000 3
b100000 E
b11 C
1"
#286000
b11011 %
#290000
0"
#295000
bz *
bz ?
bz D
bz G
b0 7
b0 =
b0 F
14
00
0-
0,
b100 C
1"
#296000
b10100010 #
b11100 %
#300000
0"
#305000
04
b101 .
b101 <
b101 J
b101 C
1"
#306000
b11101 %
#310000
0"
#315000
14
b110 C
1"
#316000
b11110 %
#320000
0"
#325000
04
b110 .
b110 <
b110 J
b111 C
1"
#326000
b11111 %
#330000
0"
#335000
b110 7
b110 =
b110 F
1,
b0 C
1"
#336000
b100000 %
#340000
0"
#345000
b100000 *
b100000 ?
b100000 D
b100000 G
1-
b1 C
1"
#346000
b100001 %
#350000
0"
#355000
10
b10111011 *
b10111011 ?
b10111011 D
b10111011 G
b10 C
b10111011 H
1"
#356000
b100010 %
#360000
0"
#365000
b10111011 6
b10111011 9
b10111011 A
b101 B
b101 @
b11011 ;
b11011 I
b10111011 3
b10111011 E
b11 C
1"
#366000
b100011 %
#370000
0"
#375000
bz 6
bz 9
bz A
bz *
bz ?
bz D
bz G
b11011 7
b11011 =
b11011 F
14
00
0-
0,
b100 C
1"
#376000
b100100 %
#380000
0"
#385000
b10111011 6
b10111011 9
b10111011 A
b10111011 *
b10111011 ?
b10111011 D
b10111011 G
04
1-
b111 .
b111 <
b111 J
b101 C
1"
#386000
b100101 %
#390000
0"
#395000
b11111111 6
b11111111 9
b11111111 A
b11111111 *
b11111111 ?
b11111111 D
b11111111 G
b110 C
b11111111 H
1"
#396000
b100110 %
#400000
0"
#405000
11
b111 C
1"
#406000
b100111 %
#410000
0"
#415000
bz 6
bz 9
bz A
bz *
bz ?
bz D
bz G
b111 7
b111 =
b111 F
01
0-
1,
02
b0 C
b11111111 8
b11111111 :
b11111111 >
1"
#416000
b101000 %
#420000
0"
#425000
b11111111 6
b11111111 9
b11111111 A
b11111111 *
b11111111 ?
b11111111 D
b11111111 G
1-
b1 C
1"
#426000
b101001 %
#430000
0"
#435000
b100000 6
b100000 9
b100000 A
10
b100000 *
b100000 ?
b100000 D
b100000 G
b10 C
b100000 H
1"
#436000
b101010 %
#440000
0"
#445000
b11111111 6
b11111111 9
b11111111 A
b1 B
b1 @
b0 ;
b0 I
b100000 3
b100000 E
b11 C
1"
#446000
b101011 %
#450000
0"
#455000
bz *
bz ?
bz D
bz G
b0 7
b0 =
b0 F
14
00
0-
0,
b100 C
1"
#456000
b101100 %
#460000
0"
#465000
04
b1000 .
b1000 <
b1000 J
b101 C
1"
#466000
b101101 %
#470000
0"
#475000
b110 C
1"
#476000
b101110 %
#480000
0"
#485000
b111 C
1"
#486000
b101111 %
#490000
0"
#495000
b1000 7
b1000 =
b1000 F
1,
b0 C
1"
#496000
b110000 %
#500000
0"
#505000
b100000 *
b100000 ?
b100000 D
b100000 G
1-
b1 C
1"
#506000
b110001 %
#510000
0"
#515000
10
b11101010 *
b11101010 ?
b11101010 D
b11101010 G
b10 C
b11101010 H
1"
#516000
b110010 %
#520000
0"
#525000
b111 B
b111 @
b1010 ;
b1010 I
b11101010 3
b11101010 E
b11 C
1"
#526000
b110011 %
#530000
0"
#535000
bz *
bz ?
bz D
bz G
b1010 7
b1010 =
b1010 F
14
00
0-
0,
b100 C
1"
#536000
b110100 %
#540000
0"
#545000
04
b1001 .
b1001 <
b1001 J
b101 C
1"
#546000
b110101 %
#550000
0"
#555000
1/
b110 C
1"
#556000
b110110 %
#560000
0"
#565000
b1010 .
b1010 <
b1010 J
b111 C
1"
#566000
b110111 %
#570000
0"
#575000
0/
1,
b0 C
1"
#576000
b111000 %
#580000
0"
#585000
b11101010 *
b11101010 ?
b11101010 D
b11101010 G
1-
b1 C
1"
#586000
b111001 %
#590000
0"
#595000
10
b11011100 *
b11011100 ?
b11011100 D
b11011100 G
b10 C
b11011100 H
1"
#596000
b111010 %
#600000
0"
#605000
b110 B
b110 @
b11100 ;
b11100 I
b11011100 3
b11011100 E
b11 C
1"
#606000
b111011 %
#610000
0"
#615000
bz *
bz ?
bz D
bz G
b11100 7
b11100 =
b11100 F
14
00
0-
0,
b100 C
1"
#616000
b11100010 #
b111100 %
#620000
0"
#625000
04
b1011 .
b1011 <
b1011 J
b101 C
1"
#626000
b111101 %
#630000
0"
#635000
b11111111 *
b11111111 ?
b11111111 D
b11111111 G
15
b110 C
1"
#636000
b111110 %
#640000
0"
#645000
1+
b111 C
1"
#646000
b111111 %
#650000
0"
#655000
bz *
bz ?
bz D
bz G
b1011 7
b1011 =
b1011 F
05
0+
1,
b0 C
1"
#656000
b1000000 %
#660000
0"
#665000
b11011100 *
b11011100 ?
b11011100 D
b11011100 G
1-
b1 C
1"
#666000
b1000001 %
#670000
0"
#675000
10
b10111010 *
b10111010 ?
b10111010 D
b10111010 G
b10 C
b10111010 H
1"
#676000
b1000010 %
#680000
0"
#685000
b10111010 6
b10111010 9
b10111010 A
b101 B
b101 @
b11010 ;
b11010 I
b10111010 3
b10111010 E
b11 C
1"
#686000
b1000011 %
#690000
0"
#695000
bz 6
bz 9
bz A
bz *
bz ?
bz D
bz G
b11010 7
b11010 =
b11010 F
14
00
0-
0,
b100 C
1"
#696000
b1000100 %
#700000
0"
#705000
b10111010 6
b10111010 9
b10111010 A
b10111010 *
b10111010 ?
b10111010 D
b10111010 G
04
1-
b1100 .
b1100 <
b1100 J
b101 C
1"
#706000
b1000101 %
#710000
0"
#715000
b0 6
b0 9
b0 A
b0 *
b0 ?
b0 D
b0 G
b110 C
b0 H
1"
#716000
b1000110 %
#720000
0"
#725000
11
b111 C
1"
#726000
b1000111 %
#730000
0"
#735000
bz 6
bz 9
bz A
bz *
bz ?
bz D
bz G
b1100 7
b1100 =
b1100 F
01
0-
1,
12
b0 C
b0 8
b0 :
b0 >
1"
#736000
b1001000 %
#740000
0"
#745000
b0 6
b0 9
b0 A
b0 *
b0 ?
b0 D
b0 G
1-
b1 C
1"
#746000
b1001001 %
#750000
0"
#755000
b11011100 6
b11011100 9
b11011100 A
10
b11011100 *
b11011100 ?
b11011100 D
b11011100 G
b10 C
b11011100 H
1"
#756000
b1001010 %
#760000
0"
#765000
b0 6
b0 9
b0 A
b110 B
b110 @
b11100 ;
b11100 I
b11011100 3
b11011100 E
b11 C
1"
#766000
b1001011 %
#770000
0"
#775000
bz *
bz ?
bz D
bz G
b11100 7
b11100 =
b11100 F
14
00
0-
0,
b100 C
1"
#776000
b1001100 %
#780000
0"
#785000
04
b1101 .
b1101 <
b1101 J
b101 C
1"
#786000
b1001101 %
#790000
0"
#795000
b0 *
b0 ?
b0 D
b0 G
15
b110 C
1"
#796000
b1001110 %
#800000
0"
#805000
1+
b111 C
1"
#806000
b1001111 %
#810000
0"
#815000
bz *
bz ?
bz D
bz G
b1101 7
b1101 =
b1101 F
05
0+
1,
b0 C
1"
#816000
b1010000 %
#820000
0"
#825000
b11011100 *
b11011100 ?
b11011100 D
b11011100 G
1-
b1 C
1"
#826000
b1010001 %
#830000
0"
#835000
10
b10111100 *
b10111100 ?
b10111100 D
b10111100 G
b10 C
b10111100 H
1"
#836000
b1010010 %
#840000
0"
#845000
b10111100 6
b10111100 9
b10111100 A
b101 B
b101 @
b10111100 3
b10111100 E
b11 C
1"
#846000
b1010011 %
#850000
0"
#855000
bz 6
bz 9
bz A
bz *
bz ?
bz D
bz G
b11100 7
b11100 =
b11100 F
14
00
0-
0,
b100 C
1"
#856000
b1010100 %
#860000
0"
#865000
b10111100 6
b10111100 9
b10111100 A
b10111100 *
b10111100 ?
b10111100 D
b10111100 G
04
1-
b1110 .
b1110 <
b1110 J
b101 C
1"
#866000
b1010101 %
#870000
0"
#875000
b0 6
b0 9
b0 A
b0 *
b0 ?
b0 D
b0 G
b110 C
b0 H
1"
#876000
b1010110 %
#880000
0"
#885000
11
b111 C
1"
#886000
b1010111 %
#890000
0"
#895000
bz 6
bz 9
bz A
bz *
bz ?
bz D
bz G
b1110 7
b1110 =
b1110 F
01
0-
1,
b0 C
1"
#896000
b1011000 %
#900000
0"
#905000
b0 6
b0 9
b0 A
b0 *
b0 ?
b0 D
b0 G
1-
b1 C
1"
#906000
b1011001 %
#910000
0"
#915000
b100000 6
b100000 9
b100000 A
10
b100000 *
b100000 ?
b100000 D
b100000 G
b10 C
b100000 H
1"
#916000
b1011010 %
#920000
0"
